RuheXuePythonLiSansi/README.md
RuheXuePythonLiSansi/__init__.py
RuheXuePythonLiSansi/__main__.py
RuheXuePythonLiSansi/file.epub
RuheXuePythonLiSansi/index.html
RuheXuePythonLiSansi/css/__init__.py
RuheXuePythonLiSansi/css/annotations.css
RuheXuePythonLiSansi/css/main.css
RuheXuePythonLiSansi/css/normalize.css
RuheXuePythonLiSansi/css/popup.css
RuheXuePythonLiSansi/font/__init__.py
RuheXuePythonLiSansi/font/fontello.eot
RuheXuePythonLiSansi/font/fontello.svg
RuheXuePythonLiSansi/font/fontello.ttf
RuheXuePythonLiSansi/font/fontello.woff
RuheXuePythonLiSansi/img/__init__.py
RuheXuePythonLiSansi/img/annotator-glyph-sprite.png
RuheXuePythonLiSansi/img/annotator-icon-sprite.png
RuheXuePythonLiSansi/img/apple-touch-icon.png
RuheXuePythonLiSansi/img/cancelfullscreen.png
RuheXuePythonLiSansi/img/close.png
RuheXuePythonLiSansi/img/fullscreen.png
RuheXuePythonLiSansi/img/loader.gif
RuheXuePythonLiSansi/img/menu-icon.png
RuheXuePythonLiSansi/img/save.png
RuheXuePythonLiSansi/img/saved.png
RuheXuePythonLiSansi/img/settings-s.png
RuheXuePythonLiSansi/img/settings.png
RuheXuePythonLiSansi/img/star.png
RuheXuePythonLiSansi/js/__init__.py
RuheXuePythonLiSansi/js/epub.js
RuheXuePythonLiSansi/js/epub.min.js
RuheXuePythonLiSansi/js/epub.min.map
RuheXuePythonLiSansi/js/hooks.min.js
RuheXuePythonLiSansi/js/hooks.min.map
RuheXuePythonLiSansi/js/reader.js
RuheXuePythonLiSansi/js/reader.js.map
RuheXuePythonLiSansi/js/reader.min.js
RuheXuePythonLiSansi/js/reader.min.map
RuheXuePythonLiSansi/js/hooks/__init__.py
RuheXuePythonLiSansi/js/hooks/extensions/__init__.py
RuheXuePythonLiSansi/js/hooks/extensions/highlight.js
RuheXuePythonLiSansi/js/libs/__init__.py
RuheXuePythonLiSansi/js/libs/jquery.min.js
RuheXuePythonLiSansi/js/libs/localforage.min.js
RuheXuePythonLiSansi/js/libs/screenfull.js
RuheXuePythonLiSansi/js/libs/screenfull.min.js
RuheXuePythonLiSansi/js/libs/zip.min.js
RuheXuePythonLiSansi/js/plugins/__init__.py
RuheXuePythonLiSansi/js/plugins/hypothesis.js
ruhe_xue_python_li_sansi-2024.3.2.0.dist-info/METADATA
ruhe_xue_python_li_sansi-2024.3.2.0.dist-info/WHEEL
ruhe_xue_python_li_sansi-2024.3.2.0.dist-info/entry_points.txt
ruhe_xue_python_li_sansi-2024.3.2.0.dist-info/top_level.txt
ruhe_xue_python_li_sansi-2024.3.2.0.dist-info/RECORD
